my_personal_spanish_conjugation_generator/__init__.py
my_personal_spanish_conjugation_generator/conjugator.py
my_personal_spanish_conjugation_generator/constants.py
my_personal_spanish_conjugation_generator/data/verbs.json
my_personal_spanish_conjugation_generator/py.typed
my_personal_spanish_conjugation_generator-0.1.1.dist-info/WHEEL
my_personal_spanish_conjugation_generator-0.1.1.dist-info/METADATA
my_personal_spanish_conjugation_generator-0.1.1.dist-info/RECORD
