Metadata-Version: 2.3
Name: my-personal-spanish-conjugation-generator
Version: 0.1.1
Summary: Spanish conjugation generator
Author: David L.
Author-email: David L. <fantaph@icloud.com>
Classifier: Development Status :: 4 - Beta
Classifier: Intended Audience :: Developers
Classifier: License :: OSI Approved :: MIT License
Classifier: Programming Language :: Python :: 3
Classifier: Programming Language :: Python :: 3.12
Classifier: Operating System :: OS Independent
Requires-Dist: pytest ; extra == 'test'
Requires-Python: >=3.12
Project-URL: Homepage, https://github.com/example/spanish-conjugator
Project-URL: Documentation, https://github.com/example/spanish-conjugator
Project-URL: Source, https://github.com/example/spanish-conjugator
Provides-Extra: test
